trivela/__init__.py
trivela/api.py
trivela/middleware.py
trivela/orm.py
trivela/response.py
trivela-0.0.5.dist-info/METADATA
trivela-0.0.5.dist-info/WHEEL
trivela-0.0.5.dist-info/top_level.txt
trivela-0.0.5.dist-info/RECORD
