Metadata-Version: 2.1
Name: trivela
Version: 0.0.5
Summary: Trivela Python Web Framework build for learning purpose.
Author: Sanjaya Rai
Author-email: rainamite@gmail.com
License: MIT
Classifier: Programming Language :: Python :: 3.12
Requires-Python: >=3.12.0
Requires-Dist: Jinja ==3.1.2
Requires-Dist: parse ==1.20.0
Requires-Dist: requests ==2.31.0
Requires-Dist: requests-wsgi-adapter ==0.4.1
Requires-Dist: WebOb ==1.8.7
Requires-Dist: whitenoise ==4.1.4
